yodi/Yodi.py
yodi/__init__.py
yodi_demo-0.0.1.dist-info/LICENSE
yodi_demo-0.0.1.dist-info/METADATA
yodi_demo-0.0.1.dist-info/WHEEL
yodi_demo-0.0.1.dist-info/top_level.txt
yodi_demo-0.0.1.dist-info/RECORD
