Metadata-Version: 2.1
Name: yodi_demo
Version: 0.0.1
License-File: LICENSE
Requires-Dist: pathlib
Requires-Dist: tensorflow
Requires-Dist: matplotlib
Requires-Dist: numpy
Requires-Dist: seaborn
Requires-Dist: IPython
Requires-Dist: gradio
